kheperax/__init__.py
kheperax/custom_types.py
kheperax/envs/__init__.py
kheperax/envs/env.py
kheperax/envs/kheperax_state.py
kheperax/envs/maze_maps.py
kheperax/envs/scoring.py
kheperax/envs/wrappers.py
kheperax/simu/__init__.py
kheperax/simu/geoms.py
kheperax/simu/laser.py
kheperax/simu/maze.py
kheperax/simu/posture.py
kheperax/simu/robot.py
kheperax/tasks/__init__.py
kheperax/tasks/config.py
kheperax/tasks/final_distance.py
kheperax/tasks/main.py
kheperax/tasks/quad.py
kheperax/tasks/target.py
kheperax/utils/__init__.py
kheperax/utils/rendering_tools.py
kheperax/utils/tree_utils.py
kheperax-0.2.0.dist-info/LICENSE
kheperax-0.2.0.dist-info/METADATA
kheperax-0.2.0.dist-info/WHEEL
kheperax-0.2.0.dist-info/top_level.txt
kheperax-0.2.0.dist-info/RECORD
