Metadata-Version: 2.1
Name: kheperax
Version: 0.2.0
Summary: A-maze-ing environment in jax
Author-email: Luca Grillotti and Paul Templier <luca.grillotti16@imperial.ac.uk>
License: MIT License
Project-URL: Homepage, https://github.com/adaptive-intelligent-robotics/Kheperax
Keywords: Quality-Diversity,Reinforcement Learning,JAX
Classifier: Development Status :: 4 - Beta
Classifier: Environment :: Console
Classifier: Intended Audience :: Science/Research
Classifier: License :: OSI Approved :: MIT License
Classifier: Operating System :: POSIX :: Linux
Classifier: Programming Language :: Python :: 3
Classifier: Programming Language :: Python :: 3.10
Classifier: Programming Language :: Python :: 3.11
Classifier: Programming Language :: Python :: 3.12
Classifier: Topic :: Scientific/Engineering :: Artificial Intelligence
Requires-Python: >=3.10
License-File: LICENSE
Requires-Dist: jax >=0.4.28
Requires-Dist: jaxlib >=0.4.28
Requires-Dist: flax >=0.8.5
Requires-Dist: qdax >=0.4.0
Requires-Dist: tqdm >=4.66.5
Requires-Dist: imageio >=2.35.1
Provides-Extra: cuda12
Requires-Dist: jax[cuda12] >=0.4.30 ; extra == 'cuda12'
